MANIFEST.in
README.txt
alias_maker.py
ez_setup.py
setup.py
LICENSE/biopython_license.txt
LICENSE/mr_demuxy_license.txt
Mr_Demuxy.egg-info/PKG-INFO
Mr_Demuxy.egg-info/SOURCES.txt
Mr_Demuxy.egg-info/dependency_links.txt
Mr_Demuxy.egg-info/top_level.txt
bin/merged_demuxer.py
bin/pe_demuxer.py
example_data/example_merged.fastq
example_data/example_pe_R1.fastq
example_data/example_pe_R2.fastq
example_data/forward_bcs.txt
example_data/reverse_bcs.txt
mr_demuxy/__init__.py
mr_demuxy/biopython.py
mr_demuxy/merged_demuxer_dist.py
mr_demuxy/pe_demuxer_dist.py
mr_demuxy/util_functions_dist.py