Metadata-Version: 1.1
Name: Mr-Demuxy
Version: 1.0.6.beta
Summary: demultiplexs combinatorially tagged reads
Home-page: UNKNOWN
Author: Daniel E. Lefever
Author-email: lefeverde@gmail.com
License: MIT
Platform: any
Classifier: Environment :: Console
Classifier: Intended Audience :: Science/Research
Classifier: Natural Language :: English
Classifier: Operating System :: POSIX
Classifier: Programming Language :: Python :: 2.7
Classifier: Topic :: Scientific/Engineering :: Bio-Informatics
